{
  "supabase_table_count": 66,
  "source_table_count": 34,
  "expected_tables_missing_in_supabase_count": 0,
  "expected_tables_missing_in_supabase_sample": [],
  "dao_detected_table_count": 11,
  "dao_tables_missing_in_supabase_count": 10,
  "dao_tables_missing_in_supabase": [
    "assignment",
    "auditlog",
    "eksekusi",
    "kesehatan",
    "observasi_tambahan",
    "petugas",
    "pohon",
    "reposisi",
    "riwayat",
    "spr_log"
  ],
  "view_missing_dependency_items": 22,
  "view_missing_dependencies": {
    "apk.v_apk_assignment->apk.v_apk_assignment": [
      "dbo.v_assignment"
    ],
    "apk.v_apk_petugas->apk.v_apk_petugas": [
      "apk.v_petugas_lahan"
    ],
    "apk.v_n_baris->apk.v_n_baris": [
      "apk.v_apk_assignment"
    ],
    "apk.v_new_nbaris->apk.v_new_nbaris": [
      "apk.v_n_baris"
    ],
    "apk.v_petugas_lahan->apk.v_petugas_lahan": [
      "dbo.petugas_lahan"
    ],
    "apk.v_pohon_terkini->apk.v_pohon_terkini": [
      "apk.v_pohon_terkini_"
    ],
    "apk.v_pohon_terkini_->apk.v_pohon_terkini_": [
      "apk.v_spk_pohon",
      "dbo.v_reposisi_terkini"
    ],
    "apk.v_ref_code->apk.v_ref_code": [
      "dbo.ref_code"
    ],
    "apk.v_simulasi_pohon->apk.v_simulasi_pohon": [
      "apk.v_spk_pohon",
      "dbo.vsim_reposisi_terkini"
    ],
    "apk.v_spk_pohon->apk.v_spk_pohon": [
      "dbo.petugas_lahan"
    ],
    "apk.v_spk_pohon_i->apk.v_spk_pohon_i": [
      "apk.v_new_nbaris"
    ],
    "dbo.v_max_reposisi->dbo.v_max_reposisi": [
      "dbo.reposisi_pohon"
    ],
    "dbo.v_max_spr->dbo.v_max_spr": [
      "dbo.stand_per_row"
    ],
    "dbo.v_pohon_tambahan->dbo.v_pohon_tambahan": [
      "dbo.reposisi_pohon"
    ],
    "dbo.v_pohon_terkini->dbo.v_pohon_terkini": [
      "dbo.reposisi_pohon"
    ],
    "dbo.v_reposisi_terkini->dbo.v_reposisi_terkini": [
      "dbo.reposisi_pohon",
      "dbo.v_max_reposisi"
    ],
    "dbo.v_spr_terkini->dbo.v_spr_terkini": [
      "dbo.v_spr_tgl_terkini"
    ],
    "dbo.v_spr_tgl_terkini->dbo.v_spr_tgl_terkini": [
      "dbo.stand_per_row",
      "dbo.v_max_spr"
    ],
    "dbo.vsim_max_reposisi->dbo.vsim_max_reposisi": [
      "dbo.reposisi_pohon"
    ],
    "dbo.vsim_pohon_tambahan->dbo.vsim_pohon_tambahan": [
      "dbo.reposisi_pohon"
    ],
    "dbo.vsim_reposisi_terkini->dbo.vsim_reposisi_terkini": [
      "dbo.reposisi_pohon",
      "dbo.vsim_max_reposisi"
    ],
    "web.vw_pohon_terkini->web.vw_pohon_terkini": [
      "dbo.v_pohon_terkini"
    ]
  }
}